{
  "_schema_version": 2,
  "title": "夏日冷萃咖啡黃金比例：在家做出好喝的冷萃",
  "slug": "cold-brew-coffee-golden-ratio-summer",
  "description": "冷萃咖啡以低溫長時間萃取的方式，減少苦澀物質的釋放，造就絲滑甜美的口感。本文提供冷萃咖啡的黃金粉水比建議，並說明影響萃取的關鍵變數，幫助你在家也能做出專業級冷萃。",
  "categories": [
    "knowledge"
  ],
  "tags": [
    "冷萃咖啡",
    "夏日咖啡",
    "自製咖啡",
    "粉水比",
    "咖啡食譜"
  ],
  "date": "2026-04-27",
  "date_modified": null,
  "body_html": "<p>炎炎夏日，一杯冰涼順口的冷萃咖啡，是許多咖啡愛好者每日的儀式感。冷萃咖啡的製作原理並不複雜：將粗研咖啡粉以冷水浸泡，透過時間替代高溫，將咖啡的甜感與果酸慢慢釋放出來，同時大幅降低苦澀物質的萃取量。以下是完整的製作方法與配方建議。</p><h2>冷萃咖啡的黃金粉水比</h2><p>冷萃咖啡最常用的粉水比是1比12至1比15之間。1比12屬於濃郁版本，適合想要兌水稀釋或加冰塊飲用的情況；1比15則是清爽版本，直接飲用就能感受到平衡的酸甜苦。</p><p>以300毫升的成品為例：使用1比12比例時，咖啡粉用量為25克；使用1比15比例時，咖啡粉用量為20克。研磨刻度建議比手衝再粗一些，落在中粗至高粗的範圍，約等同于二號砂糖的顆粒感。</p><img  src=\"/article/cold-brew-coffee-golden-ratio-summer/img-te4lmo-1.jpg\" alt=\"冷萃咖啡製作過程\" style=\"width:100%;max-width:600px;display:block;margin:1.5rem auto;\"><h2>影響冷萃風味的關鍵變數</h2><p>冷萃時間是影響風味最重要的因素。8至12小時是最常見的萃取區間，時間越長，咖啡液越厚實，但超過16小時可能開始產生過度萃取的不適苦韻。建議從12小時開始嘗試，再依個人偏好增減。</p><p>水溫方面，使用4至8°C的冷水效果最佳。若室溫低於20°C，也可以室溫萃取，但要注意可能因溫度波動而影響風味的穩定性。</p><p>咖啡豆的選擇也會大幅影響冷萃的成品表現。淺焙咖啡適合冷萃，能呈現明亮的果酸與細膩花香；中焙咖啡則能帶出均衡的巧克力與焦糖調性，適合大眾口味。</p><h2>冷萃咖啡的保存與品嚐</h2><p>冷萃咖啡完成後，建議立即過濾掉咖啡粉，並將咖啡液倒入乾淨的密封容器中，冷藏保存。冷萃咖啡在冰箱中可以保存約5至7天，但隨著時間拉長，風味會逐漸衰減。</p><p>品嚐冷萃咖啡時，可以直接飲用原液感受純粹的絲滑口感，也可以加入等量的冷水或牛奶稀釋。若想增加層次，加入一小撮海鹽能提升甜感的表現，這是許多咖啡師的秘密配方。</p><details><summary>冷萃咖啡可以用熱水加速萃取嗎？</summary><p>不建議。高溫會破壞冷萃特有的絲滑口感，並萃取出過多苦澀物質，喪失冷萃咖啡的核心價值。若趕時間，可以將咖啡粉用溫水浸濕後再加入冷水，但風味會與傳統冷萃有所差異。</p></details><details><summary>冷萃咖啡一定要用磨豆機嗎？</summary><p>不一定，但建議使用新鮮研磨的咖啡粉。預磨咖啡粉在接觸空氣後，風味會快速衰減。如果只有預磨粉，可以將萃取時間縮短2至3小時，並使用更粗的研磨刻度來補救。</p></details><details><summary>可以用即溶咖啡做冷萃嗎？</summary><p>不行。即溶咖啡已經歷過高溫萃取與乾燥程序，風味早已固定，無法透過冷萃過程重新萃取。建議使用新鮮烘焙的咖啡豆，確保冷萃成品的風味品質。</p></details><details><summary>冷萃咖啡為什麼口感特別滑順？</summary><p>因為冷水的萃取效率低，無法有效釋放咖啡中的單寧酸與苦澀多酚，這些物質正是造成咖啡苦澀與口腔澀感的元凶。低溫長時間萃取，反而能保留更多甜感分子與酸性油脂，造就冷萃特有的絲滑Body。</p></details><p>冷萃咖啡的優點，在於可以提前準備、一次大量製作，非常適合忙碌的上班族或喜歡提前備料的咖啡愛好者。掌握粉水比與萃取時間這兩個核心變數，你也能在家輕鬆衝出專業級的冷萃咖啡。</p><h2>相關文章</h2><ul><li><a href=\"/article/coffee-brewing-ratio-complete-guide\">咖啡粉水比完整攻略：找到你的專屬黃金比例</a></li><li><a href=\"/article/pour-over-coffee-bloom-technique\">手衝咖啡悶蒸技巧：讓咖啡粉充分綻放的關鍵步驟</a></li></ul>",
  "body_mode": "rich_text",
  "products": [],
  "structured_data": null,
  "source": "admin"
}
