{
  "_schema_version": 2,
  "title": "咖啡豆研磨粗細完整攻略：找到最適合你的刻度",
  "slug": "coffee-bean-grind-size-complete-guide",
  "description": "研磨粗細是影響咖啡萃取效率與風味的關鍵變數。本文說明不同刻度對應的萃取特性，以及如何根據衝煮器具調整研磨參數，幫助讀者找到最適合自己的研磨設定，避免過度萃取或萃取不足的問題。",
  "categories": [
    "knowledge"
  ],
  "tags": [
    "咖啡豆",
    "研磨粗細",
    "咖啡萃取",
    "磨豆機",
    "手沖技巧"
  ],
  "date": "2026-04-25",
  "date_modified": null,
  "body_html": "<h2>研磨粗細為什麼是咖啡萃取的核心變數</h2><p>咖啡豆研磨後，表面積瞬間擴大數百倍，熱水與咖啡粉的接觸效率直接由顆粒大小決定。顆粒越細，熱水穿透所需時間越長，萃取率越高；顆粒越粗，熱水通過速度快，萃取率相對較低。調整研磨刻度是少數可以在衝煮過程中即時影響萃取結果的變數，也是愛好者最值得投資時間鑽研的項目之一。</p><p>不同衝煮器具對研磨粗細的需求差異極大。意式咖啡機需要在 25-30 秒內萃取出 25-30 c.c. 的液體，因此需要極細的粉塵狀研磨；手沖咖啡有 2-4 分鐘的萃取時間，適合中等偏粗的顆粒；冷萃咖啡的萃取時間長達 12-24 小時，通常使用粗研磨避免過度萃取。</p><img  src=\"/article/coffee-bean-grind-size-complete-guide/img-te0w9d-1.jpg\" alt=\"咖啡研磨粗細示意\" style=\"width:100%;max-width:600px;margin:16px 0;border-radius:8px\"/><h2>如何找到適合自己的研磨刻度</h2><p>大多數磨豆機的刻度範圍從 0（最細）到 30-40（最粗），但每台機器的刻度對應實際顆粒大小並不相同。建議先從該器具的推薦刻度出發，再根據風味表現進行微調。每次調整以半格或一格為單位，紀錄衝煮參數與風味結果，逐步建立個人化的參數庫。</p><p>判斷研磨是否適當的最直接方式，是觀察萃取時間和品嚐風味。若手衝總時間低於 2 分，可能是研磨過粗導致萃取不足，可嘗試調細半格；若總時間超過 4 分，可能是研磨過細導致過度萃取，應調粗一些。風味方面，萃取不足時酸質突出、甜感薄弱；過度萃取時苦澀明顯、餘韻不佳。</p><h2>研磨均勻度與設備選擇</h2><p>除了粗細之外，顆粒均勻度對萃取品質影響同樣關鍵。鬼齒平刀或錐形刀盤的磨豆機，通常能產出均勻度較高的顆粒，風味乾淨且層次分明；廉價的砍豆機則容易產生大量細粉和極粗顆粒摻雜，導致萃取不均，風味容易帶有雜感或過度萃取的苦澀。</p><p>若想進一步提升均勻度，可考慮投資帶有篩粉器的磨豆機，或在衝煮前以篩網去除最細的顆粒（又稱「極細粉」）。這類細粉容易堵塞濾杯、造成局部過度萃取，移除後能明顯提升乾淨度。</p><details><summary>研磨過細會怎樣？</summary><p>研磨過細會大幅延長萃取時間，熱水在粉層中停留過久，萃取出過多苦澀物質和深色色素。風味上容易出現明顯的苦味、澀感和焦苦韻，嚴重時會有「咬嘴」的澀口感。</p></details><details><summary>研磨過粗會怎樣？</summary><p>研磨過粗時，熱水通過粉層的速度過快，與咖啡物質接觸不足導致萃取率偏低。風味上會感覺酸質尖銳、甜感不足、口感單薄，嚴重時會有明顯的「水味」。</p></details><details><summary>每次衝煮都要調整刻度嗎？</summary><p>除非豆子特性差異很大（新舊豆、烘焙度不同），否則建議先以既有的穩定參數衝煮，觀察風味變化再決定是否需要調整。氣溫、濕度變化也會輕微影響研磨後的表現，可留意季節性調整。</p></details><details><summary>細粉一定要篩掉嗎？</summary><p>不一定。若使用錐形濾杯（如 V60），適量細粉有時能提升口感的厚實度；若使用平底濾杯（如 Kalita），過多細粉容易堵塞通道造成通道效應，建議篩除。建議先以不篩的版本品嚐，再決定是否需要改善。</p></details>",
  "body_mode": "rich_text",
  "products": [],
  "structured_data": null,
  "source": "admin"
}
